monkeyplug/__init__.py
monkeyplug/monkeyplug.py
monkeyplug/swears.txt
monkeyplug-2.1.6.dist-info/licenses/LICENSE
monkeyplug-2.1.6.dist-info/METADATA
monkeyplug-2.1.6.dist-info/WHEEL
monkeyplug-2.1.6.dist-info/entry_points.txt
monkeyplug-2.1.6.dist-info/top_level.txt
monkeyplug-2.1.6.dist-info/RECORD
