Metadata-Version: 2.4
Name: monkeyplug
Version: 2.1.6
Summary: monkeyplug is a little script to censor profanity in audio files.
Home-page: https://github.com/mmguero/monkeyplug
Author: Seth Grover
Author-email: mero.mero.guero@gmail.com
Project-URL: Bug Tracker, https://github.com/mmguero/monkeyplug/issues
Classifier: License :: OSI Approved :: BSD License
Classifier: Operating System :: OS Independent
Classifier: Programming Language :: Python :: 3
Classifier: Topic :: Multimedia :: Sound/Audio :: Speech
Requires-Python: >=3.6
License-File: LICENSE
Requires-Dist: mmguero
Requires-Dist: mutagen
Requires-Dist: requests
Dynamic: license-file
